CHANGES
MANIFEST.in
README.rst
setup.cfg
setup.py
fly/__init__.py
fly.skels.egg-info/PKG-INFO
fly.skels.egg-info/SOURCES.txt
fly.skels.egg-info/dependency_links.txt
fly.skels.egg-info/entry_points.txt
fly.skels.egg-info/namespace_packages.txt
fly.skels.egg-info/not-zip-safe
fly.skels.egg-info/requires.txt
fly.skels.egg-info/top_level.txt
fly/skels/__init__.py
fly/skels/base.py
fly/skels/templates.py
fly/skels/tmpl/buildout/README.rst_tmpl
fly/skels/tmpl/buildout/bootstrap.py_tmpl
fly/skels/tmpl/buildout/buildout.cfg_tmpl
fly/skels/tmpl/buildout/setup.cfg_tmpl
fly/skels/tmpl/buildout/setup.py_tmpl
fly/skels/tmpl/buildout/+egg+.egg-info/paste_deploy_config.ini_tmpl
fly/skels/tmpl/buildout/+package+/__init__.py_tmpl
fly/skels/tmpl/full/README.rst_tmpl
fly/skels/tmpl/full/bootstrap.py_tmpl
fly/skels/tmpl/full/buildout.cfg_tmpl
fly/skels/tmpl/full/setup.cfg_tmpl
fly/skels/tmpl/full/setup.py_tmpl
fly/skels/tmpl/full/+egg+.egg-info/paste_deploy_config.ini_tmpl
fly/skels/tmpl/full/+namespace+/__init__.py_tmpl
fly/skels/tmpl/full/+namespace+/+python_package+/__init__.py_tmpl
fly/skels/tmpl/namespace/README.rst_tmpl
fly/skels/tmpl/namespace/setup.cfg_tmpl
fly/skels/tmpl/namespace/setup.py_tmpl
fly/skels/tmpl/namespace/+egg+.egg-info/paste_deploy_config.ini_tmpl
fly/skels/tmpl/namespace/+namespace+/__init__.py_tmpl
fly/skels/tmpl/namespace/+namespace+/+python_package+/__init__.py_tmpl