Metadata-Version: 1.1
Name: fly.skels
Version: 0.2.1
Summary: Skeletons used on fly
Home-page: http://www.flyzen.com
Author: Young King
Author-email: youngking@flyzen.com
License: BSD
Platform: UNKNOWN
Classifier: Programming Language :: Python
Classifier: Topic :: Software Development :: Libraries :: Python Modules
